{"data": {"repository": {"stargazers": {"pageInfo": {"hasNextPage": true, "endCursor": "Y3Vyc29yOnYyOpK0MjAxOS0wOS0xN1QxNjo0Mzo1MlrOCyPUMw=="}, "edges": [{"starredAt": "2019-04-15T13:45:39Z"}, {"starredAt": "2019-04-17T08:31:37Z"}, {"starredAt": "2019-04-17T08:37:40Z"}, {"starredAt": "2019-04-17T10:51:08Z"}, {"starredAt": "2019-04-18T05:57:27Z"}, {"starredAt": "2019-04-18T08:49:23Z"}, {"starredAt": "2019-04-18T09:57:50Z"}, {"starredAt": "2019-04-18T13:25:23Z"}, {"starredAt": "2019-04-19T02:56:07Z"}, {"starredAt": "2019-04-19T15:39:08Z"}, {"starredAt": "2019-04-19T17:54:24Z"}, {"starredAt": "2019-04-20T06:27:29Z"}, {"starredAt": "2019-04-20T09:28:30Z"}, {"starredAt": "2019-04-20T14:35:55Z"}, {"starredAt": "2019-04-22T09:29:59Z"}, {"starredAt": "2019-04-22T09:44:15Z"}, {"starredAt": "2019-04-22T10:32:42Z"}, {"starredAt": "2019-04-22T14:40:41Z"}, {"starredAt": "2019-04-23T01:24:32Z"}, {"starredAt": "2019-04-23T01:33:59Z"}, {"starredAt": "2019-04-23T04:52:41Z"}, {"starredAt": "2019-04-23T14:44:27Z"}, {"starredAt": "2019-04-24T01:49:27Z"}, {"starredAt": "2019-04-24T02:54:34Z"}, {"starredAt": "2019-04-24T03:32:26Z"}, {"starredAt": "2019-04-24T06:28:34Z"}, {"starredAt": "2019-04-24T11:39:37Z"}, {"starredAt": "2019-04-24T12:03:32Z"}, {"starredAt": "2019-04-24T23:29:50Z"}, {"starredAt": "2019-04-25T01:28:56Z"}, {"starredAt": "2019-04-25T02:04:24Z"}, {"starredAt": "2019-04-25T03:44:04Z"}, {"starredAt": "2019-04-25T04:53:11Z"}, {"starredAt": "2019-04-25T15:13:54Z"}, {"starredAt": "2019-04-26T09:06:54Z"}, {"starredAt": "2019-04-28T01:45:46Z"}, {"starredAt": "2019-04-28T03:30:05Z"}, {"starredAt": "2019-04-28T12:51:44Z"}, {"starredAt": "2019-04-28T23:20:09Z"}, {"starredAt": "2019-04-29T07:16:03Z"}, {"starredAt": "2019-04-30T05:00:44Z"}, {"starredAt": "2019-05-03T04:02:35Z"}, {"starredAt": "2019-05-05T13:45:04Z"}, {"starredAt": "2019-05-06T06:17:08Z"}, {"starredAt": "2019-05-06T07:28:59Z"}, {"starredAt": "2019-05-07T03:36:50Z"}, {"starredAt": "2019-05-07T09:15:00Z"}, {"starredAt": "2019-05-07T13:07:53Z"}, {"starredAt": "2019-05-10T06:48:35Z"}, {"starredAt": "2019-05-11T00:50:41Z"}, {"starredAt": "2019-05-13T09:18:26Z"}, {"starredAt": "2019-05-16T08:44:36Z"}, {"starredAt": "2019-05-20T02:34:04Z"}, {"starredAt": "2019-05-20T06:37:44Z"}, {"starredAt": "2019-05-22T13:48:38Z"}, {"starredAt": "2019-05-24T09:12:40Z"}, {"starredAt": "2019-05-25T07:46:10Z"}, {"starredAt": "2019-05-28T13:35:01Z"}, {"starredAt": "2019-05-31T06:59:40Z"}, {"starredAt": "2019-06-03T15:19:37Z"}, {"starredAt": "2019-06-06T01:51:17Z"}, {"starredAt": "2019-06-10T09:32:55Z"}, {"starredAt": "2019-06-13T03:17:23Z"}, {"starredAt": "2019-06-15T08:26:34Z"}, {"starredAt": "2019-06-18T09:46:15Z"}, {"starredAt": "2019-06-25T05:11:51Z"}, {"starredAt": "2019-07-04T09:56:53Z"}, {"starredAt": "2019-07-04T10:07:58Z"}, {"starredAt": "2019-07-05T01:49:23Z"}, {"starredAt": "2019-07-05T04:18:28Z"}, {"starredAt": "2019-07-05T05:22:20Z"}, {"starredAt": "2019-07-05T05:58:07Z"}, {"starredAt": "2019-07-05T10:15:09Z"}, {"starredAt": "2019-07-06T04:27:22Z"}, {"starredAt": "2019-07-07T06:28:31Z"}, {"starredAt": "2019-07-12T00:54:31Z"}, {"starredAt": "2019-07-12T08:32:50Z"}, {"starredAt": "2019-07-12T09:14:09Z"}, {"starredAt": "2019-07-12T09:27:20Z"}, {"starredAt": "2019-07-13T03:20:25Z"}, {"starredAt": "2019-07-15T02:20:40Z"}, {"starredAt": "2019-07-16T08:34:28Z"}, {"starredAt": "2019-07-17T02:49:02Z"}, {"starredAt": "2019-07-18T21:49:04Z"}, {"starredAt": "2019-07-19T01:45:01Z"}, {"starredAt": "2019-07-20T02:43:23Z"}, {"starredAt": "2019-07-22T15:03:46Z"}, {"starredAt": "2019-07-29T06:34:11Z"}, {"starredAt": "2019-07-30T11:48:10Z"}, {"starredAt": "2019-08-11T02:51:53Z"}, {"starredAt": "2019-08-12T03:35:53Z"}, {"starredAt": "2019-08-15T12:11:45Z"}, {"starredAt": "2019-08-19T08:43:59Z"}, {"starredAt": "2019-08-19T17:48:13Z"}, {"starredAt": "2019-08-21T11:48:50Z"}, {"starredAt": "2019-08-23T03:25:01Z"}, {"starredAt": "2019-09-11T01:20:37Z"}, {"starredAt": "2019-09-11T02:30:00Z"}, {"starredAt": "2019-09-14T04:56:52Z"}, {"starredAt": "2019-09-17T16:43:52Z"}]}}}}