{"data": {"repository": {"stargazers": {"pageInfo": {"hasNextPage": true, "endCursor": "Y3Vyc29yOnYyOpK0MjAyMS0wMy0xNlQwNzozMzo1NVrOD9e5lQ=="}, "edges": [{"starredAt": "2020-12-21T10:01:27Z"}, {"starredAt": "2020-12-22T08:10:45Z"}, {"starredAt": "2020-12-22T09:10:06Z"}, {"starredAt": "2020-12-22T15:04:51Z"}, {"starredAt": "2020-12-23T14:25:58Z"}, {"starredAt": "2020-12-23T16:14:01Z"}, {"starredAt": "2020-12-24T03:11:12Z"}, {"starredAt": "2020-12-24T06:46:09Z"}, {"starredAt": "2020-12-26T09:50:18Z"}, {"starredAt": "2020-12-26T17:20:31Z"}, {"starredAt": "2020-12-29T08:11:57Z"}, {"starredAt": "2020-12-30T09:13:56Z"}, {"starredAt": "2020-12-30T13:43:26Z"}, {"starredAt": "2020-12-31T23:10:14Z"}, {"starredAt": "2021-01-01T07:16:55Z"}, {"starredAt": "2021-01-01T13:16:46Z"}, {"starredAt": "2021-01-03T13:10:41Z"}, {"starredAt": "2021-01-04T03:48:12Z"}, {"starredAt": "2021-01-04T05:56:36Z"}, {"starredAt": "2021-01-05T08:57:00Z"}, {"starredAt": "2021-01-05T15:54:41Z"}, {"starredAt": "2021-01-06T07:50:13Z"}, {"starredAt": "2021-01-06T08:53:11Z"}, {"starredAt": "2021-01-06T09:57:17Z"}, {"starredAt": "2021-01-07T08:36:55Z"}, {"starredAt": "2021-01-08T09:11:39Z"}, {"starredAt": "2021-01-08T11:50:55Z"}, {"starredAt": "2021-01-11T07:55:39Z"}, {"starredAt": "2021-01-11T11:54:25Z"}, {"starredAt": "2021-01-12T13:24:09Z"}, {"starredAt": "2021-01-12T18:40:19Z"}, {"starredAt": "2021-01-13T09:27:21Z"}, {"starredAt": "2021-01-17T10:11:06Z"}, {"starredAt": "2021-01-17T20:44:12Z"}, {"starredAt": "2021-01-18T07:01:39Z"}, {"starredAt": "2021-01-18T13:25:03Z"}, {"starredAt": "2021-01-18T13:37:14Z"}, {"starredAt": "2021-01-19T09:37:29Z"}, {"starredAt": "2021-01-22T00:18:38Z"}, {"starredAt": "2021-01-22T14:48:57Z"}, {"starredAt": "2021-01-25T01:33:16Z"}, {"starredAt": "2021-01-25T02:16:51Z"}, {"starredAt": "2021-01-25T06:45:01Z"}, {"starredAt": "2021-01-25T14:30:56Z"}, {"starredAt": "2021-01-26T12:53:01Z"}, {"starredAt": "2021-01-27T06:48:45Z"}, {"starredAt": "2021-01-28T06:21:58Z"}, {"starredAt": "2021-01-29T10:07:30Z"}, {"starredAt": "2021-02-01T06:14:27Z"}, {"starredAt": "2021-02-03T13:35:47Z"}, {"starredAt": "2021-02-04T11:41:45Z"}, {"starredAt": "2021-02-05T03:29:06Z"}, {"starredAt": "2021-02-05T09:36:10Z"}, {"starredAt": "2021-02-08T07:27:44Z"}, {"starredAt": "2021-02-18T07:14:31Z"}, {"starredAt": "2021-02-20T01:42:40Z"}, {"starredAt": "2021-02-20T08:17:44Z"}, {"starredAt": "2021-02-20T08:23:52Z"}, {"starredAt": "2021-02-20T08:31:48Z"}, {"starredAt": "2021-02-20T08:54:34Z"}, {"starredAt": "2021-02-22T02:48:13Z"}, {"starredAt": "2021-02-22T09:11:46Z"}, {"starredAt": "2021-02-23T06:32:07Z"}, {"starredAt": "2021-02-23T09:03:33Z"}, {"starredAt": "2021-02-23T09:11:29Z"}, {"starredAt": "2021-02-23T15:33:41Z"}, {"starredAt": "2021-02-25T08:33:06Z"}, {"starredAt": "2021-02-26T01:39:07Z"}, {"starredAt": "2021-02-26T02:48:53Z"}, {"starredAt": "2021-02-26T03:21:58Z"}, {"starredAt": "2021-02-28T06:14:08Z"}, {"starredAt": "2021-03-01T02:50:06Z"}, {"starredAt": "2021-03-01T06:52:05Z"}, {"starredAt": "2021-03-01T07:42:01Z"}, {"starredAt": "2021-03-02T03:55:35Z"}, {"starredAt": "2021-03-02T04:33:17Z"}, {"starredAt": "2021-03-02T05:12:54Z"}, {"starredAt": "2021-03-02T05:51:58Z"}, {"starredAt": "2021-03-02T14:50:21Z"}, {"starredAt": "2021-03-03T02:05:02Z"}, {"starredAt": "2021-03-03T04:47:19Z"}, {"starredAt": "2021-03-03T05:10:18Z"}, {"starredAt": "2021-03-05T01:53:18Z"}, {"starredAt": "2021-03-05T10:02:02Z"}, {"starredAt": "2021-03-06T01:30:21Z"}, {"starredAt": "2021-03-06T14:56:35Z"}, {"starredAt": "2021-03-07T07:17:22Z"}, {"starredAt": "2021-03-07T12:35:48Z"}, {"starredAt": "2021-03-08T03:34:49Z"}, {"starredAt": "2021-03-08T05:33:01Z"}, {"starredAt": "2021-03-08T10:13:59Z"}, {"starredAt": "2021-03-10T13:04:09Z"}, {"starredAt": "2021-03-10T14:16:54Z"}, {"starredAt": "2021-03-11T13:56:10Z"}, {"starredAt": "2021-03-12T04:58:06Z"}, {"starredAt": "2021-03-12T05:17:49Z"}, {"starredAt": "2021-03-13T12:02:27Z"}, {"starredAt": "2021-03-15T07:48:43Z"}, {"starredAt": "2021-03-16T03:27:53Z"}, {"starredAt": "2021-03-16T07:33:55Z"}]}}}}