{"data": {"repository": {"stargazers": {"pageInfo": {"hasNextPage": true, "endCursor": "Y3Vyc29yOnYyOpK0MjAxOS0wNC0xOVQwOTowMTo0MlrOCelfZg=="}, "edges": [{"starredAt": "2019-04-18T21:20:55Z"}, {"starredAt": "2019-04-18T21:26:57Z"}, {"starredAt": "2019-04-18T21:31:29Z"}, {"starredAt": "2019-04-18T21:34:44Z"}, {"starredAt": "2019-04-18T22:01:52Z"}, {"starredAt": "2019-04-18T22:09:59Z"}, {"starredAt": "2019-04-18T22:10:44Z"}, {"starredAt": "2019-04-18T22:13:25Z"}, {"starredAt": "2019-04-18T22:18:55Z"}, {"starredAt": "2019-04-18T22:25:29Z"}, {"starredAt": "2019-04-18T22:38:24Z"}, {"starredAt": "2019-04-18T22:57:18Z"}, {"starredAt": "2019-04-18T23:00:09Z"}, {"starredAt": "2019-04-18T23:03:10Z"}, {"starredAt": "2019-04-18T23:03:20Z"}, {"starredAt": "2019-04-18T23:12:34Z"}, {"starredAt": "2019-04-18T23:24:09Z"}, {"starredAt": "2019-04-18T23:59:01Z"}, {"starredAt": "2019-04-18T23:59:29Z"}, {"starredAt": "2019-04-19T00:05:01Z"}, {"starredAt": "2019-04-19T00:09:35Z"}, {"starredAt": "2019-04-19T00:13:23Z"}, {"starredAt": "2019-04-19T00:22:37Z"}, {"starredAt": "2019-04-19T00:27:10Z"}, {"starredAt": "2019-04-19T00:28:14Z"}, {"starredAt": "2019-04-19T00:31:59Z"}, {"starredAt": "2019-04-19T00:43:08Z"}, {"starredAt": "2019-04-19T00:44:33Z"}, {"starredAt": "2019-04-19T00:45:11Z"}, {"starredAt": "2019-04-19T00:58:19Z"}, {"starredAt": "2019-04-19T00:59:07Z"}, {"starredAt": "2019-04-19T01:06:18Z"}, {"starredAt": "2019-04-19T01:14:01Z"}, {"starredAt": "2019-04-19T01:15:22Z"}, {"starredAt": "2019-04-19T01:21:04Z"}, {"starredAt": "2019-04-19T01:21:06Z"}, {"starredAt": "2019-04-19T01:51:22Z"}, {"starredAt": "2019-04-19T01:51:25Z"}, {"starredAt": "2019-04-19T01:57:10Z"}, {"starredAt": "2019-04-19T01:58:43Z"}, {"starredAt": "2019-04-19T01:59:45Z"}, {"starredAt": "2019-04-19T02:02:28Z"}, {"starredAt": "2019-04-19T02:15:46Z"}, {"starredAt": "2019-04-19T02:19:59Z"}, {"starredAt": "2019-04-19T02:21:03Z"}, {"starredAt": "2019-04-19T02:24:10Z"}, {"starredAt": "2019-04-19T02:28:31Z"}, {"starredAt": "2019-04-19T02:32:53Z"}, {"starredAt": "2019-04-19T02:34:04Z"}, {"starredAt": "2019-04-19T02:39:03Z"}, {"starredAt": "2019-04-19T02:43:34Z"}, {"starredAt": "2019-04-19T02:46:11Z"}, {"starredAt": "2019-04-19T02:46:32Z"}, {"starredAt": "2019-04-19T02:50:45Z"}, {"starredAt": "2019-04-19T02:54:38Z"}, {"starredAt": "2019-04-19T02:56:23Z"}, {"starredAt": "2019-04-19T02:57:12Z"}, {"starredAt": "2019-04-19T03:02:12Z"}, {"starredAt": "2019-04-19T03:09:22Z"}, {"starredAt": "2019-04-19T03:20:05Z"}, {"starredAt": "2019-04-19T03:36:21Z"}, {"starredAt": "2019-04-19T03:37:42Z"}, {"starredAt": "2019-04-19T03:39:00Z"}, {"starredAt": "2019-04-19T03:49:14Z"}, {"starredAt": "2019-04-19T03:50:08Z"}, {"starredAt": "2019-04-19T03:54:56Z"}, {"starredAt": "2019-04-19T03:55:26Z"}, {"starredAt": "2019-04-19T04:03:31Z"}, {"starredAt": "2019-04-19T04:30:26Z"}, {"starredAt": "2019-04-19T04:36:11Z"}, {"starredAt": "2019-04-19T04:44:01Z"}, {"starredAt": "2019-04-19T05:02:44Z"}, {"starredAt": "2019-04-19T05:23:22Z"}, {"starredAt": "2019-04-19T05:27:08Z"}, {"starredAt": "2019-04-19T05:35:13Z"}, {"starredAt": "2019-04-19T05:36:36Z"}, {"starredAt": "2019-04-19T05:38:01Z"}, {"starredAt": "2019-04-19T05:40:35Z"}, {"starredAt": "2019-04-19T05:45:10Z"}, {"starredAt": "2019-04-19T05:57:57Z"}, {"starredAt": "2019-04-19T06:06:31Z"}, {"starredAt": "2019-04-19T06:07:56Z"}, {"starredAt": "2019-04-19T06:09:56Z"}, {"starredAt": "2019-04-19T06:12:47Z"}, {"starredAt": "2019-04-19T06:29:55Z"}, {"starredAt": "2019-04-19T06:46:26Z"}, {"starredAt": "2019-04-19T07:03:29Z"}, {"starredAt": "2019-04-19T07:05:08Z"}, {"starredAt": "2019-04-19T07:55:22Z"}, {"starredAt": "2019-04-19T08:02:30Z"}, {"starredAt": "2019-04-19T08:11:20Z"}, {"starredAt": "2019-04-19T08:12:19Z"}, {"starredAt": "2019-04-19T08:20:23Z"}, {"starredAt": "2019-04-19T08:22:49Z"}, {"starredAt": "2019-04-19T08:38:55Z"}, {"starredAt": "2019-04-19T08:50:46Z"}, {"starredAt": "2019-04-19T08:52:35Z"}, {"starredAt": "2019-04-19T09:00:00Z"}, {"starredAt": "2019-04-19T09:01:41Z"}, {"starredAt": "2019-04-19T09:01:42Z"}]}}}}