{"data": {"repository": {"stargazers": {"pageInfo": {"hasNextPage": true, "endCursor": "Y3Vyc29yOnYyOpK0MjAyMC0wOS0yNlQxNToyOTowMFrODknQnw=="}, "edges": [{"starredAt": "2020-07-01T15:56:26Z"}, {"starredAt": "2020-07-02T13:56:47Z"}, {"starredAt": "2020-07-03T04:47:59Z"}, {"starredAt": "2020-07-06T09:22:01Z"}, {"starredAt": "2020-07-07T01:52:50Z"}, {"starredAt": "2020-07-07T04:04:45Z"}, {"starredAt": "2020-07-07T09:00:54Z"}, {"starredAt": "2020-07-07T12:22:25Z"}, {"starredAt": "2020-07-07T16:27:59Z"}, {"starredAt": "2020-07-08T08:33:56Z"}, {"starredAt": "2020-07-09T04:42:51Z"}, {"starredAt": "2020-07-09T10:02:04Z"}, {"starredAt": "2020-07-10T11:39:37Z"}, {"starredAt": "2020-07-11T11:13:41Z"}, {"starredAt": "2020-07-14T14:28:02Z"}, {"starredAt": "2020-07-15T19:39:59Z"}, {"starredAt": "2020-07-17T14:13:07Z"}, {"starredAt": "2020-07-18T01:48:02Z"}, {"starredAt": "2020-07-18T03:43:05Z"}, {"starredAt": "2020-07-18T17:28:25Z"}, {"starredAt": "2020-07-19T18:10:49Z"}, {"starredAt": "2020-07-21T21:18:44Z"}, {"starredAt": "2020-07-21T22:13:49Z"}, {"starredAt": "2020-07-22T11:50:58Z"}, {"starredAt": "2020-07-23T12:06:13Z"}, {"starredAt": "2020-07-23T15:28:25Z"}, {"starredAt": "2020-07-24T00:22:59Z"}, {"starredAt": "2020-07-25T07:06:53Z"}, {"starredAt": "2020-07-28T10:19:53Z"}, {"starredAt": "2020-07-28T17:46:38Z"}, {"starredAt": "2020-07-29T05:14:32Z"}, {"starredAt": "2020-07-29T07:50:38Z"}, {"starredAt": "2020-07-29T11:03:04Z"}, {"starredAt": "2020-07-30T01:54:45Z"}, {"starredAt": "2020-07-30T08:33:46Z"}, {"starredAt": "2020-07-30T08:35:21Z"}, {"starredAt": "2020-07-31T00:04:51Z"}, {"starredAt": "2020-08-02T15:08:18Z"}, {"starredAt": "2020-08-03T01:25:19Z"}, {"starredAt": "2020-08-03T02:23:25Z"}, {"starredAt": "2020-08-04T17:19:17Z"}, {"starredAt": "2020-08-05T02:36:27Z"}, {"starredAt": "2020-08-06T06:18:19Z"}, {"starredAt": "2020-08-07T02:10:53Z"}, {"starredAt": "2020-08-11T23:27:09Z"}, {"starredAt": "2020-08-12T06:15:17Z"}, {"starredAt": "2020-08-12T08:34:20Z"}, {"starredAt": "2020-08-12T14:32:28Z"}, {"starredAt": "2020-08-12T15:03:44Z"}, {"starredAt": "2020-08-13T21:05:36Z"}, {"starredAt": "2020-08-14T02:18:04Z"}, {"starredAt": "2020-08-14T03:45:31Z"}, {"starredAt": "2020-08-17T13:40:21Z"}, {"starredAt": "2020-08-19T20:30:05Z"}, {"starredAt": "2020-08-19T21:50:24Z"}, {"starredAt": "2020-08-20T09:57:13Z"}, {"starredAt": "2020-08-21T10:06:32Z"}, {"starredAt": "2020-08-21T20:56:25Z"}, {"starredAt": "2020-08-23T02:45:49Z"}, {"starredAt": "2020-08-23T08:03:33Z"}, {"starredAt": "2020-08-23T10:20:54Z"}, {"starredAt": "2020-08-23T11:12:43Z"}, {"starredAt": "2020-08-23T14:21:34Z"}, {"starredAt": "2020-08-25T14:17:08Z"}, {"starredAt": "2020-08-26T05:33:15Z"}, {"starredAt": "2020-08-26T14:47:31Z"}, {"starredAt": "2020-08-26T14:56:25Z"}, {"starredAt": "2020-08-27T15:20:30Z"}, {"starredAt": "2020-08-27T23:18:36Z"}, {"starredAt": "2020-08-28T18:11:33Z"}, {"starredAt": "2020-08-29T15:54:29Z"}, {"starredAt": "2020-08-30T03:07:17Z"}, {"starredAt": "2020-09-01T12:59:24Z"}, {"starredAt": "2020-09-02T01:30:04Z"}, {"starredAt": "2020-09-08T02:59:26Z"}, {"starredAt": "2020-09-08T14:54:41Z"}, {"starredAt": "2020-09-08T19:26:35Z"}, {"starredAt": "2020-09-09T18:29:59Z"}, {"starredAt": "2020-09-10T01:13:22Z"}, {"starredAt": "2020-09-11T07:29:30Z"}, {"starredAt": "2020-09-12T03:32:39Z"}, {"starredAt": "2020-09-13T17:31:16Z"}, {"starredAt": "2020-09-13T18:24:12Z"}, {"starredAt": "2020-09-14T11:37:51Z"}, {"starredAt": "2020-09-15T06:36:41Z"}, {"starredAt": "2020-09-16T06:04:39Z"}, {"starredAt": "2020-09-16T12:56:23Z"}, {"starredAt": "2020-09-18T03:20:05Z"}, {"starredAt": "2020-09-18T11:56:30Z"}, {"starredAt": "2020-09-18T18:38:29Z"}, {"starredAt": "2020-09-21T05:43:56Z"}, {"starredAt": "2020-09-21T06:39:36Z"}, {"starredAt": "2020-09-21T15:12:57Z"}, {"starredAt": "2020-09-21T18:15:16Z"}, {"starredAt": "2020-09-21T18:54:42Z"}, {"starredAt": "2020-09-24T02:08:56Z"}, {"starredAt": "2020-09-24T08:05:44Z"}, {"starredAt": "2020-09-24T12:14:55Z"}, {"starredAt": "2020-09-25T02:13:31Z"}, {"starredAt": "2020-09-26T15:29:00Z"}]}}}}