{"data": {"repository": {"stargazers": {"pageInfo": {"hasNextPage": true, "endCursor": "Y3Vyc29yOnYyOpK0MjAxOS0wMi0yN1QwMToxNDowOFrOCXAOgQ=="}, "edges": [{"starredAt": "2019-02-26T17:24:27Z"}, {"starredAt": "2019-02-26T17:30:04Z"}, {"starredAt": "2019-02-26T17:34:02Z"}, {"starredAt": "2019-02-26T18:11:11Z"}, {"starredAt": "2019-02-26T18:22:39Z"}, {"starredAt": "2019-02-26T18:29:15Z"}, {"starredAt": "2019-02-26T18:30:22Z"}, {"starredAt": "2019-02-26T18:31:26Z"}, {"starredAt": "2019-02-26T18:47:03Z"}, {"starredAt": "2019-02-26T18:49:49Z"}, {"starredAt": "2019-02-26T18:52:29Z"}, {"starredAt": "2019-02-26T19:05:56Z"}, {"starredAt": "2019-02-26T19:08:49Z"}, {"starredAt": "2019-02-26T19:16:59Z"}, {"starredAt": "2019-02-26T19:17:07Z"}, {"starredAt": "2019-02-26T19:17:12Z"}, {"starredAt": "2019-02-26T19:18:36Z"}, {"starredAt": "2019-02-26T19:32:04Z"}, {"starredAt": "2019-02-26T19:42:53Z"}, {"starredAt": "2019-02-26T19:45:14Z"}, {"starredAt": "2019-02-26T19:46:38Z"}, {"starredAt": "2019-02-26T19:50:22Z"}, {"starredAt": "2019-02-26T19:50:47Z"}, {"starredAt": "2019-02-26T19:53:07Z"}, {"starredAt": "2019-02-26T19:59:31Z"}, {"starredAt": "2019-02-26T20:00:09Z"}, {"starredAt": "2019-02-26T20:03:53Z"}, {"starredAt": "2019-02-26T20:12:41Z"}, {"starredAt": "2019-02-26T20:13:20Z"}, {"starredAt": "2019-02-26T20:18:17Z"}, {"starredAt": "2019-02-26T20:18:47Z"}, {"starredAt": "2019-02-26T20:21:12Z"}, {"starredAt": "2019-02-26T20:29:30Z"}, {"starredAt": "2019-02-26T20:31:59Z"}, {"starredAt": "2019-02-26T20:34:31Z"}, {"starredAt": "2019-02-26T20:37:11Z"}, {"starredAt": "2019-02-26T20:43:15Z"}, {"starredAt": "2019-02-26T20:44:03Z"}, {"starredAt": "2019-02-26T20:48:25Z"}, {"starredAt": "2019-02-26T20:48:36Z"}, {"starredAt": "2019-02-26T20:51:19Z"}, {"starredAt": "2019-02-26T20:55:40Z"}, {"starredAt": "2019-02-26T20:57:44Z"}, {"starredAt": "2019-02-26T20:58:37Z"}, {"starredAt": "2019-02-26T20:59:39Z"}, {"starredAt": "2019-02-26T21:01:10Z"}, {"starredAt": "2019-02-26T21:01:36Z"}, {"starredAt": "2019-02-26T21:01:53Z"}, {"starredAt": "2019-02-26T21:15:45Z"}, {"starredAt": "2019-02-26T21:18:38Z"}, {"starredAt": "2019-02-26T21:19:54Z"}, {"starredAt": "2019-02-26T21:42:03Z"}, {"starredAt": "2019-02-26T21:47:26Z"}, {"starredAt": "2019-02-26T21:54:13Z"}, {"starredAt": "2019-02-26T21:55:43Z"}, {"starredAt": "2019-02-26T21:57:32Z"}, {"starredAt": "2019-02-26T22:02:33Z"}, {"starredAt": "2019-02-26T22:04:35Z"}, {"starredAt": "2019-02-26T22:07:01Z"}, {"starredAt": "2019-02-26T22:10:14Z"}, {"starredAt": "2019-02-26T22:10:48Z"}, {"starredAt": "2019-02-26T22:10:51Z"}, {"starredAt": "2019-02-26T22:15:52Z"}, {"starredAt": "2019-02-26T22:17:47Z"}, {"starredAt": "2019-02-26T22:31:32Z"}, {"starredAt": "2019-02-26T22:41:35Z"}, {"starredAt": "2019-02-26T22:47:36Z"}, {"starredAt": "2019-02-26T23:00:39Z"}, {"starredAt": "2019-02-26T23:01:55Z"}, {"starredAt": "2019-02-26T23:03:37Z"}, {"starredAt": "2019-02-26T23:12:15Z"}, {"starredAt": "2019-02-26T23:13:27Z"}, {"starredAt": "2019-02-26T23:13:41Z"}, {"starredAt": "2019-02-26T23:20:26Z"}, {"starredAt": "2019-02-26T23:24:32Z"}, {"starredAt": "2019-02-26T23:27:35Z"}, {"starredAt": "2019-02-26T23:27:46Z"}, {"starredAt": "2019-02-26T23:30:37Z"}, {"starredAt": "2019-02-26T23:38:22Z"}, {"starredAt": "2019-02-26T23:48:13Z"}, {"starredAt": "2019-02-26T23:49:45Z"}, {"starredAt": "2019-02-26T23:53:54Z"}, {"starredAt": "2019-02-27T00:09:45Z"}, {"starredAt": "2019-02-27T00:10:53Z"}, {"starredAt": "2019-02-27T00:11:29Z"}, {"starredAt": "2019-02-27T00:12:24Z"}, {"starredAt": "2019-02-27T00:15:11Z"}, {"starredAt": "2019-02-27T00:16:36Z"}, {"starredAt": "2019-02-27T00:18:38Z"}, {"starredAt": "2019-02-27T00:24:25Z"}, {"starredAt": "2019-02-27T00:29:02Z"}, {"starredAt": "2019-02-27T00:53:54Z"}, {"starredAt": "2019-02-27T00:54:14Z"}, {"starredAt": "2019-02-27T00:56:49Z"}, {"starredAt": "2019-02-27T00:59:05Z"}, {"starredAt": "2019-02-27T01:02:02Z"}, {"starredAt": "2019-02-27T01:04:10Z"}, {"starredAt": "2019-02-27T01:07:33Z"}, {"starredAt": "2019-02-27T01:13:41Z"}, {"starredAt": "2019-02-27T01:14:08Z"}]}}}}