{"data": {"repository": {"stargazers": {"pageInfo": {"hasNextPage": true, "endCursor": "Y3Vyc29yOnYyOpK0MjAyMC0wNS0yNVQxMDo0MDozN1rODTO-Hg=="}, "edges": [{"starredAt": "2019-09-14T14:07:45Z"}, {"starredAt": "2019-09-19T13:00:49Z"}, {"starredAt": "2019-09-24T04:36:17Z"}, {"starredAt": "2019-09-24T19:25:41Z"}, {"starredAt": "2019-09-25T22:29:15Z"}, {"starredAt": "2019-10-05T13:12:15Z"}, {"starredAt": "2019-10-13T13:58:02Z"}, {"starredAt": "2019-10-16T03:21:33Z"}, {"starredAt": "2019-10-18T00:02:35Z"}, {"starredAt": "2019-10-20T06:34:18Z"}, {"starredAt": "2019-10-20T10:50:19Z"}, {"starredAt": "2019-10-21T14:56:57Z"}, {"starredAt": "2019-10-27T15:54:52Z"}, {"starredAt": "2019-10-27T15:59:30Z"}, {"starredAt": "2019-10-30T05:35:24Z"}, {"starredAt": "2019-11-02T08:03:39Z"}, {"starredAt": "2019-11-04T08:59:47Z"}, {"starredAt": "2019-11-05T15:11:27Z"}, {"starredAt": "2019-11-08T20:11:34Z"}, {"starredAt": "2019-11-09T08:41:42Z"}, {"starredAt": "2019-11-11T14:04:37Z"}, {"starredAt": "2019-11-14T22:24:51Z"}, {"starredAt": "2019-11-22T20:32:47Z"}, {"starredAt": "2019-11-23T14:20:56Z"}, {"starredAt": "2019-11-25T10:42:58Z"}, {"starredAt": "2019-11-25T14:34:34Z"}, {"starredAt": "2019-11-27T16:25:11Z"}, {"starredAt": "2019-11-27T20:43:52Z"}, {"starredAt": "2019-11-30T10:41:33Z"}, {"starredAt": "2019-12-02T10:38:56Z"}, {"starredAt": "2019-12-02T13:45:16Z"}, {"starredAt": "2019-12-02T20:51:21Z"}, {"starredAt": "2019-12-04T14:53:25Z"}, {"starredAt": "2019-12-08T22:20:14Z"}, {"starredAt": "2019-12-08T23:57:32Z"}, {"starredAt": "2019-12-12T17:05:16Z"}, {"starredAt": "2019-12-25T18:12:29Z"}, {"starredAt": "2019-12-27T17:05:08Z"}, {"starredAt": "2019-12-30T01:45:06Z"}, {"starredAt": "2019-12-30T12:07:14Z"}, {"starredAt": "2020-01-02T06:14:41Z"}, {"starredAt": "2020-01-04T02:08:05Z"}, {"starredAt": "2020-01-05T15:12:21Z"}, {"starredAt": "2020-01-07T07:42:19Z"}, {"starredAt": "2020-01-08T08:49:43Z"}, {"starredAt": "2020-01-09T04:32:53Z"}, {"starredAt": "2020-01-11T17:08:59Z"}, {"starredAt": "2020-01-17T12:56:38Z"}, {"starredAt": "2020-01-18T15:38:34Z"}, {"starredAt": "2020-01-20T11:26:21Z"}, {"starredAt": "2020-01-20T23:01:05Z"}, {"starredAt": "2020-01-23T22:47:54Z"}, {"starredAt": "2020-01-29T08:10:37Z"}, {"starredAt": "2020-01-30T22:37:54Z"}, {"starredAt": "2020-02-05T16:12:09Z"}, {"starredAt": "2020-02-07T15:41:00Z"}, {"starredAt": "2020-02-11T16:02:06Z"}, {"starredAt": "2020-02-12T13:35:37Z"}, {"starredAt": "2020-02-12T18:20:45Z"}, {"starredAt": "2020-02-15T12:37:21Z"}, {"starredAt": "2020-02-18T09:38:31Z"}, {"starredAt": "2020-02-19T12:12:26Z"}, {"starredAt": "2020-02-19T13:03:56Z"}, {"starredAt": "2020-02-23T14:56:30Z"}, {"starredAt": "2020-02-26T08:08:09Z"}, {"starredAt": "2020-02-29T20:58:09Z"}, {"starredAt": "2020-03-06T17:37:44Z"}, {"starredAt": "2020-03-07T02:15:58Z"}, {"starredAt": "2020-03-07T11:44:13Z"}, {"starredAt": "2020-03-11T07:18:57Z"}, {"starredAt": "2020-03-19T08:33:06Z"}, {"starredAt": "2020-03-19T16:41:46Z"}, {"starredAt": "2020-03-26T09:09:38Z"}, {"starredAt": "2020-03-26T15:39:17Z"}, {"starredAt": "2020-03-27T01:46:58Z"}, {"starredAt": "2020-03-31T21:42:02Z"}, {"starredAt": "2020-04-07T12:14:03Z"}, {"starredAt": "2020-04-12T10:47:44Z"}, {"starredAt": "2020-04-15T14:06:40Z"}, {"starredAt": "2020-04-17T19:15:12Z"}, {"starredAt": "2020-04-30T04:09:51Z"}, {"starredAt": "2020-04-30T08:24:05Z"}, {"starredAt": "2020-05-04T15:38:04Z"}, {"starredAt": "2020-05-05T03:53:27Z"}, {"starredAt": "2020-05-05T21:41:07Z"}, {"starredAt": "2020-05-06T15:24:31Z"}, {"starredAt": "2020-05-09T01:39:32Z"}, {"starredAt": "2020-05-12T07:55:17Z"}, {"starredAt": "2020-05-15T13:35:32Z"}, {"starredAt": "2020-05-16T06:14:02Z"}, {"starredAt": "2020-05-16T15:05:45Z"}, {"starredAt": "2020-05-19T10:50:35Z"}, {"starredAt": "2020-05-20T07:22:53Z"}, {"starredAt": "2020-05-21T07:27:56Z"}, {"starredAt": "2020-05-23T02:27:09Z"}, {"starredAt": "2020-05-23T10:56:12Z"}, {"starredAt": "2020-05-24T08:46:40Z"}, {"starredAt": "2020-05-24T22:02:10Z"}, {"starredAt": "2020-05-25T10:23:57Z"}, {"starredAt": "2020-05-25T10:40:37Z"}]}}}}