{"data": {"repository": {"stargazers": {"pageInfo": {"hasNextPage": true, "endCursor": "Y3Vyc29yOnYyOpK0MjAxOS0wNy0wMlQwMjo0NDo0NFrOCoXEiA=="}, "edges": [{"starredAt": "2019-07-02T02:09:32Z"}, {"starredAt": "2019-07-02T02:09:34Z"}, {"starredAt": "2019-07-02T02:10:07Z"}, {"starredAt": "2019-07-02T02:10:14Z"}, {"starredAt": "2019-07-02T02:10:40Z"}, {"starredAt": "2019-07-02T02:10:52Z"}, {"starredAt": "2019-07-02T02:11:00Z"}, {"starredAt": "2019-07-02T02:11:26Z"}, {"starredAt": "2019-07-02T02:11:27Z"}, {"starredAt": "2019-07-02T02:11:40Z"}, {"starredAt": "2019-07-02T02:11:45Z"}, {"starredAt": "2019-07-02T02:12:13Z"}, {"starredAt": "2019-07-02T02:12:39Z"}, {"starredAt": "2019-07-02T02:12:40Z"}, {"starredAt": "2019-07-02T02:12:50Z"}, {"starredAt": "2019-07-02T02:13:01Z"}, {"starredAt": "2019-07-02T02:13:09Z"}, {"starredAt": "2019-07-02T02:13:12Z"}, {"starredAt": "2019-07-02T02:14:06Z"}, {"starredAt": "2019-07-02T02:14:47Z"}, {"starredAt": "2019-07-02T02:14:49Z"}, {"starredAt": "2019-07-02T02:15:40Z"}, {"starredAt": "2019-07-02T02:15:58Z"}, {"starredAt": "2019-07-02T02:16:02Z"}, {"starredAt": "2019-07-02T02:16:23Z"}, {"starredAt": "2019-07-02T02:16:37Z"}, {"starredAt": "2019-07-02T02:16:57Z"}, {"starredAt": "2019-07-02T02:17:04Z"}, {"starredAt": "2019-07-02T02:17:04Z"}, {"starredAt": "2019-07-02T02:17:10Z"}, {"starredAt": "2019-07-02T02:17:50Z"}, {"starredAt": "2019-07-02T02:18:06Z"}, {"starredAt": "2019-07-02T02:18:10Z"}, {"starredAt": "2019-07-02T02:18:30Z"}, {"starredAt": "2019-07-02T02:19:02Z"}, {"starredAt": "2019-07-02T02:19:25Z"}, {"starredAt": "2019-07-02T02:19:30Z"}, {"starredAt": "2019-07-02T02:19:44Z"}, {"starredAt": "2019-07-02T02:20:26Z"}, {"starredAt": "2019-07-02T02:20:31Z"}, {"starredAt": "2019-07-02T02:21:09Z"}, {"starredAt": "2019-07-02T02:21:28Z"}, {"starredAt": "2019-07-02T02:21:54Z"}, {"starredAt": "2019-07-02T02:22:00Z"}, {"starredAt": "2019-07-02T02:22:08Z"}, {"starredAt": "2019-07-02T02:22:14Z"}, {"starredAt": "2019-07-02T02:23:19Z"}, {"starredAt": "2019-07-02T02:23:33Z"}, {"starredAt": "2019-07-02T02:23:48Z"}, {"starredAt": "2019-07-02T02:24:01Z"}, {"starredAt": "2019-07-02T02:24:12Z"}, {"starredAt": "2019-07-02T02:24:18Z"}, {"starredAt": "2019-07-02T02:24:22Z"}, {"starredAt": "2019-07-02T02:24:24Z"}, {"starredAt": "2019-07-02T02:24:28Z"}, {"starredAt": "2019-07-02T02:26:13Z"}, {"starredAt": "2019-07-02T02:26:25Z"}, {"starredAt": "2019-07-02T02:26:35Z"}, {"starredAt": "2019-07-02T02:26:35Z"}, {"starredAt": "2019-07-02T02:26:57Z"}, {"starredAt": "2019-07-02T02:27:19Z"}, {"starredAt": "2019-07-02T02:27:30Z"}, {"starredAt": "2019-07-02T02:28:10Z"}, {"starredAt": "2019-07-02T02:29:02Z"}, {"starredAt": "2019-07-02T02:29:20Z"}, {"starredAt": "2019-07-02T02:29:53Z"}, {"starredAt": "2019-07-02T02:30:02Z"}, {"starredAt": "2019-07-02T02:30:13Z"}, {"starredAt": "2019-07-02T02:31:29Z"}, {"starredAt": "2019-07-02T02:31:38Z"}, {"starredAt": "2019-07-02T02:31:45Z"}, {"starredAt": "2019-07-02T02:31:50Z"}, {"starredAt": "2019-07-02T02:32:20Z"}, {"starredAt": "2019-07-02T02:32:27Z"}, {"starredAt": "2019-07-02T02:32:45Z"}, {"starredAt": "2019-07-02T02:32:59Z"}, {"starredAt": "2019-07-02T02:33:29Z"}, {"starredAt": "2019-07-02T02:34:32Z"}, {"starredAt": "2019-07-02T02:35:49Z"}, {"starredAt": "2019-07-02T02:35:50Z"}, {"starredAt": "2019-07-02T02:36:12Z"}, {"starredAt": "2019-07-02T02:36:12Z"}, {"starredAt": "2019-07-02T02:36:34Z"}, {"starredAt": "2019-07-02T02:36:53Z"}, {"starredAt": "2019-07-02T02:37:01Z"}, {"starredAt": "2019-07-02T02:37:24Z"}, {"starredAt": "2019-07-02T02:37:37Z"}, {"starredAt": "2019-07-02T02:37:50Z"}, {"starredAt": "2019-07-02T02:38:44Z"}, {"starredAt": "2019-07-02T02:39:05Z"}, {"starredAt": "2019-07-02T02:39:17Z"}, {"starredAt": "2019-07-02T02:40:46Z"}, {"starredAt": "2019-07-02T02:41:27Z"}, {"starredAt": "2019-07-02T02:41:46Z"}, {"starredAt": "2019-07-02T02:41:53Z"}, {"starredAt": "2019-07-02T02:41:55Z"}, {"starredAt": "2019-07-02T02:42:38Z"}, {"starredAt": "2019-07-02T02:43:48Z"}, {"starredAt": "2019-07-02T02:44:16Z"}, {"starredAt": "2019-07-02T02:44:44Z"}]}}}}