{"data": {"repository": {"stargazers": {"pageInfo": {"hasNextPage": true, "endCursor": "Y3Vyc29yOnYyOpK0MjAxOS0wNC0wNlQxMzo0NDozNFrOCcnfhw=="}, "edges": [{"starredAt": "2019-03-16T04:11:43Z"}, {"starredAt": "2019-03-16T07:25:01Z"}, {"starredAt": "2019-03-16T09:03:42Z"}, {"starredAt": "2019-03-16T13:22:23Z"}, {"starredAt": "2019-03-16T15:25:30Z"}, {"starredAt": "2019-03-16T16:01:50Z"}, {"starredAt": "2019-03-16T17:57:44Z"}, {"starredAt": "2019-03-16T20:18:21Z"}, {"starredAt": "2019-03-16T22:15:11Z"}, {"starredAt": "2019-03-17T05:15:07Z"}, {"starredAt": "2019-03-17T06:20:10Z"}, {"starredAt": "2019-03-17T15:05:08Z"}, {"starredAt": "2019-03-17T17:02:25Z"}, {"starredAt": "2019-03-18T03:55:01Z"}, {"starredAt": "2019-03-18T13:24:05Z"}, {"starredAt": "2019-03-18T18:03:59Z"}, {"starredAt": "2019-03-18T22:33:10Z"}, {"starredAt": "2019-03-18T23:06:07Z"}, {"starredAt": "2019-03-19T01:45:44Z"}, {"starredAt": "2019-03-19T09:08:35Z"}, {"starredAt": "2019-03-19T10:09:53Z"}, {"starredAt": "2019-03-19T12:44:48Z"}, {"starredAt": "2019-03-19T15:32:40Z"}, {"starredAt": "2019-03-19T17:25:27Z"}, {"starredAt": "2019-03-19T18:34:18Z"}, {"starredAt": "2019-03-19T19:02:13Z"}, {"starredAt": "2019-03-20T10:18:52Z"}, {"starredAt": "2019-03-20T12:13:59Z"}, {"starredAt": "2019-03-20T15:32:59Z"}, {"starredAt": "2019-03-20T16:17:49Z"}, {"starredAt": "2019-03-20T19:05:48Z"}, {"starredAt": "2019-03-20T23:50:32Z"}, {"starredAt": "2019-03-20T23:52:25Z"}, {"starredAt": "2019-03-21T08:56:16Z"}, {"starredAt": "2019-03-21T13:55:32Z"}, {"starredAt": "2019-03-21T16:47:38Z"}, {"starredAt": "2019-03-21T16:52:01Z"}, {"starredAt": "2019-03-21T19:28:37Z"}, {"starredAt": "2019-03-21T21:36:44Z"}, {"starredAt": "2019-03-22T15:53:04Z"}, {"starredAt": "2019-03-22T19:33:16Z"}, {"starredAt": "2019-03-23T22:16:22Z"}, {"starredAt": "2019-03-24T00:45:16Z"}, {"starredAt": "2019-03-24T13:46:34Z"}, {"starredAt": "2019-03-24T15:59:00Z"}, {"starredAt": "2019-03-24T16:36:07Z"}, {"starredAt": "2019-03-24T18:32:00Z"}, {"starredAt": "2019-03-24T23:30:25Z"}, {"starredAt": "2019-03-25T03:11:14Z"}, {"starredAt": "2019-03-25T07:05:26Z"}, {"starredAt": "2019-03-25T11:24:19Z"}, {"starredAt": "2019-03-25T14:55:32Z"}, {"starredAt": "2019-03-26T01:23:54Z"}, {"starredAt": "2019-03-26T11:16:04Z"}, {"starredAt": "2019-03-26T12:56:55Z"}, {"starredAt": "2019-03-26T15:03:27Z"}, {"starredAt": "2019-03-26T17:00:55Z"}, {"starredAt": "2019-03-26T20:33:00Z"}, {"starredAt": "2019-03-26T21:02:19Z"}, {"starredAt": "2019-03-27T03:31:09Z"}, {"starredAt": "2019-03-27T07:03:43Z"}, {"starredAt": "2019-03-27T08:14:19Z"}, {"starredAt": "2019-03-27T08:36:26Z"}, {"starredAt": "2019-03-27T18:14:42Z"}, {"starredAt": "2019-03-27T22:58:23Z"}, {"starredAt": "2019-03-28T00:48:25Z"}, {"starredAt": "2019-03-28T03:48:02Z"}, {"starredAt": "2019-03-28T05:51:52Z"}, {"starredAt": "2019-03-28T20:49:38Z"}, {"starredAt": "2019-03-28T22:48:39Z"}, {"starredAt": "2019-03-29T02:33:28Z"}, {"starredAt": "2019-03-29T15:55:44Z"}, {"starredAt": "2019-03-30T14:10:04Z"}, {"starredAt": "2019-03-30T17:34:48Z"}, {"starredAt": "2019-03-30T23:09:32Z"}, {"starredAt": "2019-03-31T18:50:09Z"}, {"starredAt": "2019-03-31T21:35:14Z"}, {"starredAt": "2019-03-31T23:40:21Z"}, {"starredAt": "2019-04-01T00:27:21Z"}, {"starredAt": "2019-04-01T08:18:27Z"}, {"starredAt": "2019-04-01T17:05:59Z"}, {"starredAt": "2019-04-01T18:25:58Z"}, {"starredAt": "2019-04-02T01:34:52Z"}, {"starredAt": "2019-04-03T07:45:21Z"}, {"starredAt": "2019-04-03T10:08:21Z"}, {"starredAt": "2019-04-03T16:11:40Z"}, {"starredAt": "2019-04-03T16:30:55Z"}, {"starredAt": "2019-04-03T16:44:20Z"}, {"starredAt": "2019-04-03T19:22:33Z"}, {"starredAt": "2019-04-03T21:55:05Z"}, {"starredAt": "2019-04-04T06:05:47Z"}, {"starredAt": "2019-04-04T15:47:08Z"}, {"starredAt": "2019-04-04T16:53:39Z"}, {"starredAt": "2019-04-04T17:48:46Z"}, {"starredAt": "2019-04-04T19:24:26Z"}, {"starredAt": "2019-04-04T20:18:09Z"}, {"starredAt": "2019-04-05T02:23:42Z"}, {"starredAt": "2019-04-05T14:09:25Z"}, {"starredAt": "2019-04-05T18:18:42Z"}, {"starredAt": "2019-04-06T13:44:34Z"}]}}}}