{"data": {"repository": {"stargazers": {"pageInfo": {"hasNextPage": true, "endCursor": "Y3Vyc29yOnYyOpK0MjAyMC0wMy0zMVQwNjoxNzo1M1rODKu4DA=="}, "edges": [{"starredAt": "2020-03-06T00:03:39Z"}, {"starredAt": "2020-03-06T03:10:09Z"}, {"starredAt": "2020-03-06T20:26:40Z"}, {"starredAt": "2020-03-06T21:17:05Z"}, {"starredAt": "2020-03-07T13:22:28Z"}, {"starredAt": "2020-03-07T16:24:37Z"}, {"starredAt": "2020-03-07T23:11:44Z"}, {"starredAt": "2020-03-08T09:42:08Z"}, {"starredAt": "2020-03-08T15:34:41Z"}, {"starredAt": "2020-03-08T15:48:55Z"}, {"starredAt": "2020-03-08T18:01:30Z"}, {"starredAt": "2020-03-08T19:43:32Z"}, {"starredAt": "2020-03-09T03:08:11Z"}, {"starredAt": "2020-03-09T15:35:24Z"}, {"starredAt": "2020-03-10T07:12:47Z"}, {"starredAt": "2020-03-11T09:26:29Z"}, {"starredAt": "2020-03-12T07:06:43Z"}, {"starredAt": "2020-03-12T08:37:44Z"}, {"starredAt": "2020-03-13T15:40:24Z"}, {"starredAt": "2020-03-13T20:57:30Z"}, {"starredAt": "2020-03-14T11:03:51Z"}, {"starredAt": "2020-03-14T17:02:03Z"}, {"starredAt": "2020-03-14T17:16:14Z"}, {"starredAt": "2020-03-14T19:46:08Z"}, {"starredAt": "2020-03-15T00:01:28Z"}, {"starredAt": "2020-03-15T02:01:16Z"}, {"starredAt": "2020-03-15T02:12:44Z"}, {"starredAt": "2020-03-15T06:07:28Z"}, {"starredAt": "2020-03-15T07:31:04Z"}, {"starredAt": "2020-03-15T09:41:25Z"}, {"starredAt": "2020-03-15T11:38:06Z"}, {"starredAt": "2020-03-15T12:27:35Z"}, {"starredAt": "2020-03-15T16:00:43Z"}, {"starredAt": "2020-03-15T18:53:06Z"}, {"starredAt": "2020-03-16T00:20:09Z"}, {"starredAt": "2020-03-16T17:04:33Z"}, {"starredAt": "2020-03-16T17:21:46Z"}, {"starredAt": "2020-03-16T18:23:31Z"}, {"starredAt": "2020-03-16T18:57:01Z"}, {"starredAt": "2020-03-16T20:34:49Z"}, {"starredAt": "2020-03-18T07:45:31Z"}, {"starredAt": "2020-03-18T13:04:56Z"}, {"starredAt": "2020-03-18T15:12:37Z"}, {"starredAt": "2020-03-18T19:55:40Z"}, {"starredAt": "2020-03-19T07:50:09Z"}, {"starredAt": "2020-03-20T08:59:53Z"}, {"starredAt": "2020-03-21T06:56:28Z"}, {"starredAt": "2020-03-21T17:33:10Z"}, {"starredAt": "2020-03-22T22:43:25Z"}, {"starredAt": "2020-03-23T18:30:58Z"}, {"starredAt": "2020-03-23T18:52:18Z"}, {"starredAt": "2020-03-23T19:17:34Z"}, {"starredAt": "2020-03-23T21:14:59Z"}, {"starredAt": "2020-03-23T23:07:37Z"}, {"starredAt": "2020-03-24T00:16:30Z"}, {"starredAt": "2020-03-24T02:51:11Z"}, {"starredAt": "2020-03-24T07:02:23Z"}, {"starredAt": "2020-03-24T10:08:38Z"}, {"starredAt": "2020-03-24T12:30:53Z"}, {"starredAt": "2020-03-24T20:08:01Z"}, {"starredAt": "2020-03-24T21:42:18Z"}, {"starredAt": "2020-03-26T21:20:06Z"}, {"starredAt": "2020-03-27T15:15:16Z"}, {"starredAt": "2020-03-27T18:40:34Z"}, {"starredAt": "2020-03-27T20:09:37Z"}, {"starredAt": "2020-03-28T08:15:56Z"}, {"starredAt": "2020-03-28T10:22:06Z"}, {"starredAt": "2020-03-28T15:00:53Z"}, {"starredAt": "2020-03-28T20:08:21Z"}, {"starredAt": "2020-03-28T21:06:18Z"}, {"starredAt": "2020-03-28T22:08:31Z"}, {"starredAt": "2020-03-29T06:42:46Z"}, {"starredAt": "2020-03-29T09:17:36Z"}, {"starredAt": "2020-03-29T13:15:32Z"}, {"starredAt": "2020-03-29T13:50:20Z"}, {"starredAt": "2020-03-29T14:14:24Z"}, {"starredAt": "2020-03-29T15:21:20Z"}, {"starredAt": "2020-03-29T15:40:42Z"}, {"starredAt": "2020-03-29T15:40:53Z"}, {"starredAt": "2020-03-29T15:59:59Z"}, {"starredAt": "2020-03-29T18:19:05Z"}, {"starredAt": "2020-03-29T19:02:41Z"}, {"starredAt": "2020-03-29T19:08:49Z"}, {"starredAt": "2020-03-29T20:07:10Z"}, {"starredAt": "2020-03-29T20:55:04Z"}, {"starredAt": "2020-03-30T00:21:35Z"}, {"starredAt": "2020-03-30T02:03:22Z"}, {"starredAt": "2020-03-30T02:29:20Z"}, {"starredAt": "2020-03-30T05:11:56Z"}, {"starredAt": "2020-03-30T05:45:27Z"}, {"starredAt": "2020-03-30T06:31:09Z"}, {"starredAt": "2020-03-30T08:20:51Z"}, {"starredAt": "2020-03-30T10:08:20Z"}, {"starredAt": "2020-03-30T10:50:18Z"}, {"starredAt": "2020-03-30T11:32:24Z"}, {"starredAt": "2020-03-30T18:14:33Z"}, {"starredAt": "2020-03-30T18:39:21Z"}, {"starredAt": "2020-03-30T19:54:12Z"}, {"starredAt": "2020-03-31T01:37:20Z"}, {"starredAt": "2020-03-31T06:17:53Z"}]}}}}