{"data": {"repository": {"stargazers": {"pageInfo": {"hasNextPage": true, "endCursor": "Y3Vyc29yOnYyOpK0MjAyMS0wMS0yMVQxMzo0NzoyM1rOD1VJGg=="}, "edges": [{"starredAt": "2020-10-19T06:35:25Z"}, {"starredAt": "2020-10-19T11:21:24Z"}, {"starredAt": "2020-10-19T12:59:21Z"}, {"starredAt": "2020-10-21T01:15:08Z"}, {"starredAt": "2020-10-21T06:34:58Z"}, {"starredAt": "2020-10-21T07:27:42Z"}, {"starredAt": "2020-10-21T08:09:47Z"}, {"starredAt": "2020-10-21T09:22:26Z"}, {"starredAt": "2020-10-22T08:05:42Z"}, {"starredAt": "2020-10-26T02:59:37Z"}, {"starredAt": "2020-10-26T05:51:25Z"}, {"starredAt": "2020-10-27T13:46:56Z"}, {"starredAt": "2020-10-29T01:31:16Z"}, {"starredAt": "2020-10-29T08:49:43Z"}, {"starredAt": "2020-10-29T09:15:43Z"}, {"starredAt": "2020-11-02T01:37:53Z"}, {"starredAt": "2020-11-02T06:49:17Z"}, {"starredAt": "2020-11-04T11:47:55Z"}, {"starredAt": "2020-11-05T01:38:36Z"}, {"starredAt": "2020-11-05T10:22:58Z"}, {"starredAt": "2020-11-05T23:31:45Z"}, {"starredAt": "2020-11-09T07:49:55Z"}, {"starredAt": "2020-11-10T15:27:48Z"}, {"starredAt": "2020-11-11T04:54:16Z"}, {"starredAt": "2020-11-13T11:44:53Z"}, {"starredAt": "2020-11-14T14:49:17Z"}, {"starredAt": "2020-11-15T14:19:01Z"}, {"starredAt": "2020-11-15T22:55:26Z"}, {"starredAt": "2020-11-16T02:37:01Z"}, {"starredAt": "2020-11-16T14:36:04Z"}, {"starredAt": "2020-11-17T12:39:08Z"}, {"starredAt": "2020-11-18T07:53:25Z"}, {"starredAt": "2020-11-19T07:11:43Z"}, {"starredAt": "2020-11-19T08:17:20Z"}, {"starredAt": "2020-11-22T08:58:20Z"}, {"starredAt": "2020-11-24T02:34:45Z"}, {"starredAt": "2020-11-24T13:08:41Z"}, {"starredAt": "2020-11-26T05:48:19Z"}, {"starredAt": "2020-11-27T01:44:20Z"}, {"starredAt": "2020-11-28T14:08:39Z"}, {"starredAt": "2020-11-29T05:38:13Z"}, {"starredAt": "2020-11-30T00:03:15Z"}, {"starredAt": "2020-11-30T02:07:21Z"}, {"starredAt": "2020-11-30T03:13:46Z"}, {"starredAt": "2020-11-30T08:29:03Z"}, {"starredAt": "2020-11-30T09:18:19Z"}, {"starredAt": "2020-12-01T12:23:33Z"}, {"starredAt": "2020-12-01T14:17:42Z"}, {"starredAt": "2020-12-02T10:13:02Z"}, {"starredAt": "2020-12-02T16:58:30Z"}, {"starredAt": "2020-12-03T16:56:01Z"}, {"starredAt": "2020-12-04T07:47:50Z"}, {"starredAt": "2020-12-04T09:28:59Z"}, {"starredAt": "2020-12-06T12:38:27Z"}, {"starredAt": "2020-12-07T01:24:27Z"}, {"starredAt": "2020-12-07T14:48:11Z"}, {"starredAt": "2020-12-11T02:49:57Z"}, {"starredAt": "2020-12-13T09:03:57Z"}, {"starredAt": "2020-12-14T06:01:21Z"}, {"starredAt": "2020-12-15T09:36:42Z"}, {"starredAt": "2020-12-16T14:28:41Z"}, {"starredAt": "2020-12-16T21:24:57Z"}, {"starredAt": "2020-12-17T02:16:03Z"}, {"starredAt": "2020-12-17T08:20:03Z"}, {"starredAt": "2020-12-22T02:37:41Z"}, {"starredAt": "2020-12-22T07:30:42Z"}, {"starredAt": "2020-12-23T01:43:37Z"}, {"starredAt": "2020-12-28T02:02:43Z"}, {"starredAt": "2020-12-28T11:04:09Z"}, {"starredAt": "2020-12-29T13:10:16Z"}, {"starredAt": "2021-01-01T15:07:15Z"}, {"starredAt": "2021-01-03T03:03:43Z"}, {"starredAt": "2021-01-03T13:37:47Z"}, {"starredAt": "2021-01-04T09:44:04Z"}, {"starredAt": "2021-01-04T15:28:39Z"}, {"starredAt": "2021-01-04T20:43:38Z"}, {"starredAt": "2021-01-05T05:20:40Z"}, {"starredAt": "2021-01-05T07:02:42Z"}, {"starredAt": "2021-01-05T09:51:44Z"}, {"starredAt": "2021-01-05T10:03:32Z"}, {"starredAt": "2021-01-05T17:42:07Z"}, {"starredAt": "2021-01-06T11:13:05Z"}, {"starredAt": "2021-01-07T06:51:09Z"}, {"starredAt": "2021-01-10T05:49:01Z"}, {"starredAt": "2021-01-10T19:26:21Z"}, {"starredAt": "2021-01-11T09:27:10Z"}, {"starredAt": "2021-01-11T22:10:21Z"}, {"starredAt": "2021-01-13T02:48:10Z"}, {"starredAt": "2021-01-13T17:47:08Z"}, {"starredAt": "2021-01-14T00:46:29Z"}, {"starredAt": "2021-01-15T01:58:27Z"}, {"starredAt": "2021-01-17T14:09:10Z"}, {"starredAt": "2021-01-17T18:14:47Z"}, {"starredAt": "2021-01-18T09:19:37Z"}, {"starredAt": "2021-01-18T10:56:50Z"}, {"starredAt": "2021-01-19T02:49:25Z"}, {"starredAt": "2021-01-19T06:46:01Z"}, {"starredAt": "2021-01-20T06:20:19Z"}, {"starredAt": "2021-01-21T01:21:01Z"}, {"starredAt": "2021-01-21T13:47:23Z"}]}}}}