{"data": {"repository": {"stargazers": {"pageInfo": {"hasNextPage": true, "endCursor": "Y3Vyc29yOnYyOpK0MjAyMC0xMC0xOVQxNzoyNzozNlrODnrEhg=="}, "edges": [{"starredAt": "2020-05-09T11:38:21Z"}, {"starredAt": "2020-05-11T12:00:59Z"}, {"starredAt": "2020-05-14T00:54:55Z"}, {"starredAt": "2020-05-14T03:35:58Z"}, {"starredAt": "2020-05-14T19:00:15Z"}, {"starredAt": "2020-05-15T15:34:35Z"}, {"starredAt": "2020-05-15T20:20:49Z"}, {"starredAt": "2020-05-17T08:32:27Z"}, {"starredAt": "2020-05-17T20:39:40Z"}, {"starredAt": "2020-05-18T17:06:23Z"}, {"starredAt": "2020-05-19T08:04:37Z"}, {"starredAt": "2020-05-24T11:57:28Z"}, {"starredAt": "2020-05-24T19:41:56Z"}, {"starredAt": "2020-05-28T04:37:14Z"}, {"starredAt": "2020-05-28T17:03:35Z"}, {"starredAt": "2020-05-31T07:52:10Z"}, {"starredAt": "2020-06-03T14:53:46Z"}, {"starredAt": "2020-06-04T09:14:52Z"}, {"starredAt": "2020-06-07T02:51:19Z"}, {"starredAt": "2020-06-08T06:20:15Z"}, {"starredAt": "2020-06-13T16:08:57Z"}, {"starredAt": "2020-06-14T11:49:33Z"}, {"starredAt": "2020-06-24T02:59:28Z"}, {"starredAt": "2020-06-24T04:14:37Z"}, {"starredAt": "2020-06-26T22:26:37Z"}, {"starredAt": "2020-06-27T13:39:09Z"}, {"starredAt": "2020-06-28T03:55:06Z"}, {"starredAt": "2020-06-29T20:31:58Z"}, {"starredAt": "2020-07-02T17:35:32Z"}, {"starredAt": "2020-07-05T05:56:22Z"}, {"starredAt": "2020-07-06T14:51:14Z"}, {"starredAt": "2020-07-09T17:46:27Z"}, {"starredAt": "2020-07-10T22:05:16Z"}, {"starredAt": "2020-07-14T01:46:22Z"}, {"starredAt": "2020-07-15T04:50:26Z"}, {"starredAt": "2020-07-18T11:55:15Z"}, {"starredAt": "2020-07-18T12:59:12Z"}, {"starredAt": "2020-07-19T09:01:41Z"}, {"starredAt": "2020-07-21T03:56:21Z"}, {"starredAt": "2020-07-21T08:20:45Z"}, {"starredAt": "2020-07-22T15:47:58Z"}, {"starredAt": "2020-07-23T19:48:57Z"}, {"starredAt": "2020-07-26T11:27:07Z"}, {"starredAt": "2020-07-26T12:22:30Z"}, {"starredAt": "2020-07-27T09:59:05Z"}, {"starredAt": "2020-07-28T22:27:32Z"}, {"starredAt": "2020-07-29T14:35:58Z"}, {"starredAt": "2020-07-30T18:08:26Z"}, {"starredAt": "2020-07-31T19:02:30Z"}, {"starredAt": "2020-08-03T07:19:39Z"}, {"starredAt": "2020-08-06T11:14:47Z"}, {"starredAt": "2020-08-07T02:45:33Z"}, {"starredAt": "2020-08-07T13:42:02Z"}, {"starredAt": "2020-08-08T08:31:59Z"}, {"starredAt": "2020-08-09T21:52:30Z"}, {"starredAt": "2020-08-16T13:46:59Z"}, {"starredAt": "2020-08-16T19:05:34Z"}, {"starredAt": "2020-08-18T13:08:16Z"}, {"starredAt": "2020-08-19T20:54:23Z"}, {"starredAt": "2020-08-20T02:45:02Z"}, {"starredAt": "2020-08-20T15:58:48Z"}, {"starredAt": "2020-08-20T18:06:19Z"}, {"starredAt": "2020-08-21T00:32:13Z"}, {"starredAt": "2020-08-21T21:05:13Z"}, {"starredAt": "2020-08-31T00:12:02Z"}, {"starredAt": "2020-09-03T04:43:40Z"}, {"starredAt": "2020-09-05T17:29:19Z"}, {"starredAt": "2020-09-06T10:01:58Z"}, {"starredAt": "2020-09-06T11:57:09Z"}, {"starredAt": "2020-09-07T11:39:33Z"}, {"starredAt": "2020-09-07T12:39:39Z"}, {"starredAt": "2020-09-07T12:46:27Z"}, {"starredAt": "2020-09-07T14:27:56Z"}, {"starredAt": "2020-09-07T18:36:31Z"}, {"starredAt": "2020-09-09T15:27:37Z"}, {"starredAt": "2020-09-10T05:55:46Z"}, {"starredAt": "2020-09-13T20:01:48Z"}, {"starredAt": "2020-09-15T20:23:09Z"}, {"starredAt": "2020-09-18T20:40:27Z"}, {"starredAt": "2020-09-23T01:06:40Z"}, {"starredAt": "2020-09-23T11:37:47Z"}, {"starredAt": "2020-09-24T21:02:34Z"}, {"starredAt": "2020-09-25T10:43:21Z"}, {"starredAt": "2020-09-25T12:53:09Z"}, {"starredAt": "2020-09-25T17:04:23Z"}, {"starredAt": "2020-09-27T06:13:44Z"}, {"starredAt": "2020-09-27T14:57:06Z"}, {"starredAt": "2020-09-28T07:18:47Z"}, {"starredAt": "2020-09-28T15:01:12Z"}, {"starredAt": "2020-09-30T08:28:47Z"}, {"starredAt": "2020-09-30T17:19:34Z"}, {"starredAt": "2020-10-09T07:33:28Z"}, {"starredAt": "2020-10-11T17:29:08Z"}, {"starredAt": "2020-10-12T03:08:46Z"}, {"starredAt": "2020-10-14T02:48:54Z"}, {"starredAt": "2020-10-15T21:21:49Z"}, {"starredAt": "2020-10-16T06:48:28Z"}, {"starredAt": "2020-10-16T21:54:46Z"}, {"starredAt": "2020-10-18T04:46:35Z"}, {"starredAt": "2020-10-19T17:27:36Z"}]}}}}