{"data": {"repository": {"stargazers": {"pageInfo": {"hasNextPage": true, "endCursor": "Y3Vyc29yOnYyOpK0MjAxOS0wNi0xNlQxMzo1NDoyM1rOCmaC9g=="}, "edges": [{"starredAt": "2019-05-13T05:45:20Z"}, {"starredAt": "2019-05-13T05:47:04Z"}, {"starredAt": "2019-05-13T06:06:12Z"}, {"starredAt": "2019-05-13T06:33:57Z"}, {"starredAt": "2019-05-13T07:02:21Z"}, {"starredAt": "2019-05-13T08:11:53Z"}, {"starredAt": "2019-05-13T09:05:42Z"}, {"starredAt": "2019-05-13T10:38:58Z"}, {"starredAt": "2019-05-13T13:59:15Z"}, {"starredAt": "2019-05-13T15:08:31Z"}, {"starredAt": "2019-05-13T15:37:46Z"}, {"starredAt": "2019-05-13T15:57:10Z"}, {"starredAt": "2019-05-14T02:10:53Z"}, {"starredAt": "2019-05-14T02:20:46Z"}, {"starredAt": "2019-05-14T03:17:09Z"}, {"starredAt": "2019-05-14T04:27:21Z"}, {"starredAt": "2019-05-14T06:05:05Z"}, {"starredAt": "2019-05-14T07:05:23Z"}, {"starredAt": "2019-05-14T15:33:03Z"}, {"starredAt": "2019-05-14T17:53:01Z"}, {"starredAt": "2019-05-14T18:16:57Z"}, {"starredAt": "2019-05-15T01:51:09Z"}, {"starredAt": "2019-05-15T03:06:15Z"}, {"starredAt": "2019-05-15T04:31:55Z"}, {"starredAt": "2019-05-15T05:03:22Z"}, {"starredAt": "2019-05-15T05:03:27Z"}, {"starredAt": "2019-05-15T08:30:47Z"}, {"starredAt": "2019-05-15T12:58:09Z"}, {"starredAt": "2019-05-15T13:01:09Z"}, {"starredAt": "2019-05-15T13:22:38Z"}, {"starredAt": "2019-05-15T14:17:03Z"}, {"starredAt": "2019-05-15T15:43:44Z"}, {"starredAt": "2019-05-15T16:20:50Z"}, {"starredAt": "2019-05-15T16:40:54Z"}, {"starredAt": "2019-05-15T20:51:46Z"}, {"starredAt": "2019-05-16T04:43:18Z"}, {"starredAt": "2019-05-16T05:00:26Z"}, {"starredAt": "2019-05-16T06:47:44Z"}, {"starredAt": "2019-05-16T07:18:16Z"}, {"starredAt": "2019-05-16T08:20:55Z"}, {"starredAt": "2019-05-16T08:38:44Z"}, {"starredAt": "2019-05-16T08:40:09Z"}, {"starredAt": "2019-05-16T11:33:21Z"}, {"starredAt": "2019-05-16T17:25:32Z"}, {"starredAt": "2019-05-16T22:59:38Z"}, {"starredAt": "2019-05-17T05:49:24Z"}, {"starredAt": "2019-05-17T06:03:51Z"}, {"starredAt": "2019-05-17T14:03:40Z"}, {"starredAt": "2019-05-17T15:08:10Z"}, {"starredAt": "2019-05-17T18:18:38Z"}, {"starredAt": "2019-05-17T19:52:31Z"}, {"starredAt": "2019-05-17T21:54:32Z"}, {"starredAt": "2019-05-18T03:03:14Z"}, {"starredAt": "2019-05-18T13:15:37Z"}, {"starredAt": "2019-05-18T20:47:06Z"}, {"starredAt": "2019-05-18T23:09:56Z"}, {"starredAt": "2019-05-19T07:46:30Z"}, {"starredAt": "2019-05-20T08:43:49Z"}, {"starredAt": "2019-05-20T13:54:04Z"}, {"starredAt": "2019-05-20T19:15:56Z"}, {"starredAt": "2019-05-21T09:31:11Z"}, {"starredAt": "2019-05-21T20:24:36Z"}, {"starredAt": "2019-05-22T07:23:29Z"}, {"starredAt": "2019-05-22T08:39:42Z"}, {"starredAt": "2019-05-22T09:03:32Z"}, {"starredAt": "2019-05-22T21:30:16Z"}, {"starredAt": "2019-05-22T23:04:38Z"}, {"starredAt": "2019-05-23T18:07:54Z"}, {"starredAt": "2019-05-23T19:05:25Z"}, {"starredAt": "2019-05-24T12:02:14Z"}, {"starredAt": "2019-05-24T18:40:13Z"}, {"starredAt": "2019-05-28T13:53:41Z"}, {"starredAt": "2019-05-29T14:06:38Z"}, {"starredAt": "2019-05-29T20:23:25Z"}, {"starredAt": "2019-05-30T22:59:58Z"}, {"starredAt": "2019-05-31T07:30:13Z"}, {"starredAt": "2019-05-31T15:20:51Z"}, {"starredAt": "2019-06-02T07:02:04Z"}, {"starredAt": "2019-06-03T22:28:18Z"}, {"starredAt": "2019-06-04T02:34:01Z"}, {"starredAt": "2019-06-04T05:22:15Z"}, {"starredAt": "2019-06-04T15:52:07Z"}, {"starredAt": "2019-06-05T15:55:02Z"}, {"starredAt": "2019-06-06T19:56:32Z"}, {"starredAt": "2019-06-06T21:20:58Z"}, {"starredAt": "2019-06-07T08:13:57Z"}, {"starredAt": "2019-06-07T10:27:17Z"}, {"starredAt": "2019-06-07T11:29:43Z"}, {"starredAt": "2019-06-07T14:14:10Z"}, {"starredAt": "2019-06-07T20:49:28Z"}, {"starredAt": "2019-06-08T13:54:41Z"}, {"starredAt": "2019-06-10T05:07:07Z"}, {"starredAt": "2019-06-10T08:43:50Z"}, {"starredAt": "2019-06-10T20:35:47Z"}, {"starredAt": "2019-06-11T06:28:16Z"}, {"starredAt": "2019-06-12T00:02:00Z"}, {"starredAt": "2019-06-12T00:29:56Z"}, {"starredAt": "2019-06-12T21:34:09Z"}, {"starredAt": "2019-06-15T19:04:56Z"}, {"starredAt": "2019-06-16T13:54:23Z"}]}}}}